{
  "settings": {
    "enableRemixiconsLine": true,
    "enableRemixiconsFill": false,
    "enableFontawesomeFill": false,
    "enableFontawesomeLine": false,
    "enableFontawesomeBrands": false,
    "fontSize": 17,
    "iconColor": null,
    "extraPadding": {
      "top": 2,
      "right": 2,
      "bottom": 2,
      "left": 2
    },
    "recentlyUsedIcons": [],
    "recentlyUsedIconsSize": 5,
    "migrated": 6,
    "iconPacksPath": ".obsidian/plugins/obsidian-icon-folder/icons",
    "rules": [],
    "extraMargin": {
      "top": 2,
      "right": 2,
      "bottom": 2,
      "left": 2
    },
    "emojiStyle": "native",
    "iconInTabsEnabled": true,
    "iconInTitleEnabled": true,
    "iconInTitlePosition": "above",
    "iconInFrontmatterEnabled": true,
    "iconInFrontmatterFieldName": "icon",
    "iconColorInFrontmatterFieldName": "iconColor",
    "iconsBackgroundCheckEnabled": false,
    "iconsInNotesEnabled": true,
    "iconsInLinksEnabled": true,
    "iconIdentifier": ":",
    "lucideIconPackType": "native",
    "debugMode": false,
    "useInternalPlugins": false
  },
  "07-Archives": "RiArchiveLine",
  "06-Cards": "RiDatabase2Line",
  "05-Life": "RiLeafLine"
}